{
	"pages": [ //pages数组中第一项表示应用启动页，参考：https://uniapp.dcloud.io/collocation/pages
		{
			"path": "pages/index/index",
			"style": {
				"navigationBarTitleText": "uni-app",
				"enablePullDownRefresh":true
			}
		},
		{
			"path": "pages/mine/mine",
			"style": {
				"navigationBarTitleText": "个人中心",
				"enablePullDownRefresh":true
				
			}
		},
		{
			"path": "pages/mine/message/msg",
			"style": {
				"navigationBarTitleText": "消息",
				"enablePullDownRefresh":true
			}
		},
		{
			
			"path": "pages/index/collapse/collapse",
			"style": {
				"navigationBarTitleText": "折叠控件的使用",
				"enablePullDownRefresh":false
			}
		},
		{
			
			"path": "pages/index/scrollView/scrollView",
			"style": {
				"navigationBarTitleText": "滑动视图的使用",
				"enablePullDownRefresh":false
			}
		},
		{
			
			"path": "pages/index/swiper/swiper",
			"style": {
				"navigationBarTitleText": "swiper-view 制作banner效果",
				"enablePullDownRefresh":false
			}
		},
		{
			
			"path": "pages/index/media/media",
			"style": {
				"navigationBarTitleText": "常用的多媒体应用",
				"enablePullDownRefresh":false
			}
		},
		{
			"path": "pages/index/map/map",
			"style": {
				"navigationBarTitleText": "地图",
				"enablePullDownRefresh":false
			}
		},
		{
			"path": "pages/index/webview/webview",
			"style": {
				"navigationBarTitleText": "webview使用",
				"enablePullDownRefresh":false
			}
		},
		{
			"path": "pages/index/refresh/refresh",
			"style": {
				"navigationBarTitleText": "下拉刷新的使用（使用自定义组件）",
				"enablePullDownRefresh":false,
				"app-plus" : {
				"bounce" : "none" 
				}
			}
		},
		{
			"path": "pages/index/collectionView/collectionView",
			"style": {
				"navigationBarTitleText": "九宫格",
				"enablePullDownRefresh":false,
			}
		}
	],
	"globalStyle": {
		"navigationBarTextStyle": "black",
		"navigationBarTitleText": "uni-app",
		"navigationBarBackgroundColor": "#F8F8F8",
		"backgroundColor": "#F8F8F8"
	},
	"tabBar":{
	"color": "#000000",
	"selectedColor": "#2F85FC",
	"backgroundColor": "#FFFFFF",
	"borderStyle": "black",
	"list":
	[
		{
			"pagePath": "pages/index/index",
			"iconPath": "static/tab_project@2x.png",
			"selectedIconPath": "static/tab_project_select@2x.png",
			"text": "首页"
		},
		{
			"pagePath": "pages/mine/mine",
			"iconPath": "static/tab_mine@2x.png",
			"selectedIconPath": "static/tab_mine_select@2x.png",
			"text": "我的"
		}
	]
	}
}
